[{"Title":"Bulas de medicamentos com a letra: A","uppercase":"A","borderb_URL":"https://consultaremedios.com.br/adriblastina-rd/bula","borderb":"Bula do Adriblastina RD","borderb_URL1":"https://consultaremedios.com.br/amaryl/bula","borderb2":"Bula do Amaryl","borderb_URL3":"https://consultaremedios.com.br/aracytin/bula","borderb4":"Bula do Aracytin","borderb_URL5":"https://consultaremedios.com.br/afinitor/bula","borderb6":"Bula do Afinitor","borderb_URL7":"https://consultaremedios.com.br/arifenicol/bula","borderb8":"Bula do Arifenicol","borderb_URL9":"https://consultaremedios.com.br/azulfin/bula","borderb10":"Bula do Azulfin","borderb_URL11":"https://consultaremedios.com.br/atropion/bula","borderb12":"Bula do Atropion","borderb_URL13":"https://consultaremedios.com.br/azeus/bula","borderb14":"Bula do Azeus","borderb_URL15":"https://consultaremedios.com.br/alimta/bula","borderb16":"Bula do Alimta","borderb_URL17":"https://consultaremedios.com.br/aclasta/bula","borderb18":"Bula do Aclasta","borderb_URL19":"https://consultaremedios.com.br/adenocard/bula","borderb20":"Bula do Adenocard","borderb_URL21":"https://consultaremedios.com.br/asalit/bula","borderb22":"Bula do Asalit","borderb_URL23":"https://consultaremedios.com.br/arflex-retard/bula","borderb24":"Bula do Arflex Retard","borderb_URL25":"https://consultaremedios.com.br/ambisome/bula","borderb26":"Bula do AmBisome","borderb_URL27":"https://consultaremedios.com.br/atacand/bula","borderb28":"Bula do Atacand","borderb_URL29":"https://consultaremedios.com.br/air-salonpas/bula","borderb30":"Bula do Air Salonpas","borderb_URL31":"https://consultaremedios.com.br/agrastat/bula","borderb32":"Bula do Agrastat","borderb_URL33":"https://consultaremedios.com.br/ascaridil/bula","borderb34":"Bula do Ascaridil","borderb_URL35":"https://consultaremedios.com.br/activelle/bula","borderb36":"Bula do Activelle","borderb_URL37":"https://consultaremedios.com.br/atacand-hct/bula","borderb38":"Bula do Atacand HCT","btn_URL":"https://consultaremedios.com.br/bulas/a","btn":"TUDO COM A LETRA: A"},{"Title":"Bulas de medicamentos com a letra: B","uppercase":"B","borderb_URL":"https://consultaremedios.com.br/benzetacil/bula","borderb":"Bula do Benzetacil","borderb_URL1":"https://consultaremedios.com.br/betnovate-q/bula","borderb2":"Bula do Betnovate Q","borderb_URL3":"https://consultaremedios.com.br/biomag/bula","borderb4":"Bula do Biomag","borderb_URL5":"https://consultaremedios.com.br/baraclude/bula","borderb6":"Bula do Baraclude","borderb_URL7":"https://consultaremedios.com.br/byetta/bula","borderb8":"Bula do Byetta","borderb_URL9":"https://consultaremedios.com.br/becenun/bula","borderb10":"Bula do Becenun","borderb_URL11":"https://consultaremedios.com.br/bacteracin-f/bula","borderb12":"Bula do Bacteracin F","borderb_URL13":"https://consultaremedios.com.br/belscopan/bula","borderb14":"Bula do Belscopan","borderb_URL15":"https://consultaremedios.com.br/benalet-tsc/bula","borderb16":"Bula do Benalet TSC","borderb_URL17":"https://consultaremedios.com.br/babymed/bula","borderb18":"Bula do Babymed","borderb_URL19":"https://consultaremedios.com.br/bacsulfaprim/bula","borderb20":"Bula do Bacsulfaprim","borderb_URL21":"https://consultaremedios.com.br/bactocilin/bula","borderb22":"Bula do Bactocilin","borderb_URL23":"https://consultaremedios.com.br/bactrim/bula","borderb24":"Bula do Bactrim","borderb_URL25":"https://consultaremedios.com.br/bart-h/bula","borderb26":"Bula do Bart H","borderb_URL27":"https://consultaremedios.com.br/benectrin/bula","borderb28":"Bula do Benectrin","borderb_URL29":"https://consultaremedios.com.br/benzin/bula","borderb30":"Bula do Benzin","borderb_URL31":"https://consultaremedios.com.br/berberis-homaccord/bula","borderb32":"Bula do Berberis-Homaccord","borderb_URL33":"https://consultaremedios.com.br/beserol/bula","borderb34":"Bula do Beserol","borderb_URL35":"https://consultaremedios.com.br/betametasona-prati-donaduzzi/bula","borderb36":"Bula do Betametasona Prati-Donaduzzi","borderb_URL37":"https://consultaremedios.com.br/baclon/bula","borderb38":"Bula do Baclon","btn_URL":"https://consultaremedios.com.br/bulas/b","btn":"TUDO COM A LETRA: B"},{"Title":"Bulas de medicamentos com a letra: C","uppercase":"C","borderb_URL":"https://consultaremedios.com.br/carbolitium/bula","borderb":"Bula do Carbolitium","borderb_URL1":"https://consultaremedios.com.br/claforan/bula","borderb2":"Bula do Claforan","borderb_URL3":"https://consultaremedios.com.br/cobavital/bula","borderb4":"Bula do Cobavital","borderb_URL5":"https://consultaremedios.com.br/coumadin/bula","borderb6":"Bula do Coumadin","borderb_URL7":"https://consultaremedios.com.br/claritin-d/bula","borderb8":"Bula do Claritin D","borderb_URL9":"https://consultaremedios.com.br/clorana/bula","borderb10":"Bula do Clorana","borderb_URL11":"https://consultaremedios.com.br/combivent/bula","borderb12":"Bula do Combivent","borderb_URL13":"https://consultaremedios.com.br/crinone/bula","borderb14":"Bula do Crinone","borderb_URL15":"https://consultaremedios.com.br/carduran-xl/bula","borderb16":"Bula do Carduran XL","borderb_URL17":"https://consultaremedios.com.br/cizax/bula","borderb18":"Bula do Cizax","borderb_URL19":"https://consultaremedios.com.br/cortisonal-injetavel/bula","borderb20":"Bula do Cortisonal Injetável","borderb_URL21":"https://consultaremedios.com.br/cromolerg/bula","borderb22":"Bula do Cromolerg","borderb_URL23":"https://consultaremedios.com.br/cyclofemina/bula","borderb24":"Bula do Cyclofemina","borderb_URL25":"https://consultaremedios.com.br/cymevene/bula","borderb26":"Bula do Cymevene","borderb_URL27":"https://consultaremedios.com.br/clomid/bula","borderb28":"Bula do Clomid","borderb_URL29":"https://consultaremedios.com.br/cronomet/bula","borderb30":"Bula do Cronomet","borderb_URL31":"https://consultaremedios.com.br/co-renitec/bula","borderb32":"Bula do Co Renitec","borderb_URL33":"https://consultaremedios.com.br/caladryl/bula","borderb34":"Bula do Caladryl","borderb_URL35":"https://consultaremedios.com.br/canesten/bula","borderb36":"Bula do Canesten","borderb_URL37":"https://consultaremedios.com.br/cellcept/bula","borderb38":"Bula do CellCept","btn_URL":"https://consultaremedios.com.br/bulas/c","btn":"TUDO COM A LETRA: C"},{"Title":"Bulas de medicamentos com a letra: D","uppercase":"D","borderb_URL":"https://consultaremedios.com.br/depo-provera/bula","borderb":"Bula do Depo Provera","borderb_URL1":"https://consultaremedios.com.br/dermazine/bula","borderb2":"Bula do Dermazine","borderb_URL3":"https://consultaremedios.com.br/dormonid-comprimido/bula","borderb4":"Bula do Dormonid Comprimido","borderb_URL5":"https://consultaremedios.com.br/dacarb/bula","borderb6":"Bula do Dacarb","borderb_URL7":"https://consultaremedios.com.br/depakene/bula","borderb8":"Bula do Depakene","borderb_URL9":"https://consultaremedios.com.br/dermomax/bula","borderb10":"Bula do Dermomax","borderb_URL11":"https://consultaremedios.com.br/diamox/bula","borderb12":"Bula do Diamox","borderb_URL13":"https://consultaremedios.com.br/diprogenta/bula","borderb14":"Bula do Diprogenta","borderb_URL15":"https://consultaremedios.com.br/dostinex/bula","borderb16":"Bula do Dostinex","borderb_URL17":"https://consultaremedios.com.br/ddavp-comprimido/bula","borderb18":"Bula do Ddavp Comprimido","borderb_URL19":"https://consultaremedios.com.br/diprosalic/bula","borderb20":"Bula do Diprosalic","borderb_URL21":"https://consultaremedios.com.br/dobutrex/bula","borderb22":"Bula do Dobutrex","borderb_URL23":"https://consultaremedios.com.br/dicetel/bula","borderb24":"Bula do Dicetel","borderb_URL25":"https://consultaremedios.com.br/daktarin/bula","borderb26":"Bula do Daktarin","borderb_URL27":"https://consultaremedios.com.br/diabinese/bula","borderb28":"Bula do Diabinese","borderb_URL29":"https://consultaremedios.com.br/diovan-hct/bula","borderb30":"Bula do Diovan HCT","borderb_URL31":"https://consultaremedios.com.br/dorflex/bula","borderb32":"Bula do Dorflex","borderb_URL33":"https://consultaremedios.com.br/dilacoron/bula","borderb34":"Bula do Dilacoron","borderb_URL35":"https://consultaremedios.com.br/decadron/bula","borderb36":"Bula do Decadron","borderb_URL37":"https://consultaremedios.com.br/daunoblastina/bula","borderb38":"Bula do Daunoblastina","btn_URL":"https://consultaremedios.com.br/bulas/d","btn":"TUDO COM A LETRA: D"},{"Title":"Bulas de medicamentos com a letra: E","uppercase":"E","borderb_URL":"https://consultaremedios.com.br/ezetrol/bula","borderb":"Bula do Ezetrol","borderb_URL1":"https://consultaremedios.com.br/ergotrate/bula","borderb2":"Bula do Ergotrate","borderb_URL3":"https://consultaremedios.com.br/exelon/bula","borderb4":"Bula do Exelon","borderb_URL5":"https://consultaremedios.com.br/evanor/bula","borderb6":"Bula do Evanor","borderb_URL7":"https://consultaremedios.com.br/ebix/bula","borderb8":"Bula do Ebix","borderb_URL9":"https://consultaremedios.com.br/elocom/bula","borderb10":"Bula do Elocom","borderb_URL11":"https://consultaremedios.com.br/equilid/bula","borderb12":"Bula do Equilid","borderb_URL13":"https://consultaremedios.com.br/eulexin/bula","borderb14":"Bula do Eulexin","borderb_URL15":"https://consultaremedios.com.br/efexor-xr/bula","borderb16":"Bula do Efexor XR","borderb_URL17":"https://consultaremedios.com.br/efortil/bula","borderb18":"Bula do Efortil","borderb_URL19":"https://consultaremedios.com.br/estomazil-pastilha/bula","borderb20":"Bula do Estomazil Pastilha","borderb_URL21":"https://consultaremedios.com.br/escabin/bula","borderb22":"Bula do Escabin","borderb_URL23":"https://consultaremedios.com.br/eloxatin/bula","borderb24":"Bula do Eloxatin","borderb_URL25":"https://consultaremedios.com.br/emla/bula","borderb26":"Bula do Emla","borderb_URL27":"https://consultaremedios.com.br/epivir-comprimido/bula","borderb28":"Bula do Epivir Comprimido","borderb_URL29":"https://consultaremedios.com.br/excedrin/bula","borderb30":"Bula do Excedrin","borderb_URL31":"https://consultaremedios.com.br/esmeron/bula","borderb32":"Bula do Esmeron","borderb_URL33":"https://consultaremedios.com.br/ethamolin/bula","borderb34":"Bula do Ethamolin","borderb_URL35":"https://consultaremedios.com.br/elidel/bula","borderb36":"Bula do Elidel","borderb_URL37":"https://consultaremedios.com.br/esperson-n/bula","borderb38":"Bula do Esperson N","btn_URL":"https://consultaremedios.com.br/bulas/e","btn":"TUDO COM A LETRA: E"},{"Title":"Bulas de medicamentos com a letra: F","uppercase":"F","borderb_URL":"https://consultaremedios.com.br/famox/bula","borderb":"Bula do Famox Comprimido","borderb_URL1":"https://consultaremedios.com.br/fenergan-comprimido/bula","borderb2":"Bula do Fenergan Comprimido","borderb_URL3":"https://consultaremedios.com.br/flodin-duo/bula","borderb4":"Bula do Flodin Duo","borderb_URL5":"https://consultaremedios.com.br/flogoral-pastilha/bula","borderb6":"Bula do Flogoral Pastilha","borderb_URL7":"https://consultaremedios.com.br/frademicina/bula","borderb8":"Bula do Frademicina","borderb_URL9":"https://consultaremedios.com.br/fluimucil/bula","borderb10":"Bula do Fluimucil","borderb_URL11":"https://consultaremedios.com.br/fresh-tears/bula","borderb12":"Bula do Fresh Tears","borderb_URL13":"https://consultaremedios.com.br/flixonase/bula","borderb14":"Bula do Flixonase","borderb_URL15":"https://consultaremedios.com.br/farmorubicina-rd/bula","borderb16":"Bula do Farmorubicina RD","borderb_URL17":"https://consultaremedios.com.br/fludara/bula","borderb18":"Bula do Fludara","borderb_URL19":"https://consultaremedios.com.br/femoston-conti/bula","borderb20":"Bula do Femoston Conti","borderb_URL21":"https://consultaremedios.com.br/floxacin/bula","borderb22":"Bula do Floxacin","borderb_URL23":"https://consultaremedios.com.br/foraseq/bula","borderb24":"Bula do Foraseq","borderb_URL25":"https://consultaremedios.com.br/fortaz/bula","borderb26":"Bula do Fortaz","borderb_URL27":"https://consultaremedios.com.br/femme-folico/bula","borderb28":"Bula do Femme Fólico","borderb_URL29":"https://consultaremedios.com.br/flagyl-nistatina/bula","borderb30":"Bula do Flagyl Nistatina","borderb_URL31":"https://consultaremedios.com.br/fentanil/bula","borderb32":"Bula do Fentanil","borderb_URL33":"https://consultaremedios.com.br/fentizol/bula","borderb34":"Bula do Fentizol","borderb_URL35":"https://consultaremedios.com.br/flatex/bula","borderb36":"Bula do Flatex","borderb_URL37":"https://consultaremedios.com.br/florate/bula","borderb38":"Bula do Florate","btn_URL":"https://consultaremedios.com.br/bulas/f","btn":"TUDO COM A LETRA: F"},{"Title":"Bulas de medicamentos com a letra: G","uppercase":"G","borderb_URL":"https://consultaremedios.com.br/galvus-met/bula","borderb":"Bula do Galvus Met","borderb_URL1":"https://consultaremedios.com.br/gino-pletil/bula","borderb2":"Bula do Gino-Pletil","borderb_URL3":"https://consultaremedios.com.br/guttalax/bula","borderb4":"Bula do Guttalax","borderb_URL5":"https://consultaremedios.com.br/gemzar/bula","borderb6":"Bula do Gemzar","borderb_URL7":"https://consultaremedios.com.br/glifage/bula","borderb8":"Bula do Glifage","borderb_URL9":"https://consultaremedios.com.br/glitisol/bula","borderb10":"Bula do Glitisol","borderb_URL11":"https://consultaremedios.com.br/gonapeptyl-daily/bula","borderb12":"Bula do Gonapeptyl Daily","borderb_URL13":"https://consultaremedios.com.br/gyno-icaden/bula","borderb14":"Bula do Gyno-Icaden","borderb_URL15":"https://consultaremedios.com.br/glucovance/bula","borderb16":"Bula do Glucovance","borderb_URL17":"https://consultaremedios.com.br/gyno-fungix/bula","borderb18":"Bula do Gyno-Fungix","borderb_URL19":"https://consultaremedios.com.br/garamicina-injetavel/bula","borderb20":"Bula do Garamicina Injetável","borderb_URL21":"https://consultaremedios.com.br/gracial/bula","borderb22":"Bula do Gracial","borderb_URL23":"https://consultaremedios.com.br/glypressin/bula","borderb24":"Bula do Glypressin","borderb_URL25":"https://consultaremedios.com.br/galvus/bula","borderb26":"Bula do Galvus","borderb_URL27":"https://consultaremedios.com.br/gliocort/bula","borderb28":"Bula do Gliocort","borderb_URL29":"https://consultaremedios.com.br/gadovist/bula","borderb30":"Bula do Gadovist","borderb_URL31":"https://consultaremedios.com.br/genteal/bula","borderb32":"Bula do GenTeal","borderb_URL33":"https://consultaremedios.com.br/glicerin/bula","borderb34":"Bula do Glicerin","borderb_URL35":"https://consultaremedios.com.br/glimepirida-accord-farma/bula","borderb36":"Bula do Glimepirida Accord Farma","borderb_URL37":"https://consultaremedios.com.br/gob6/bula","borderb38":"Bula do Gob6","btn_URL":"https://consultaremedios.com.br/bulas/g","btn":"TUDO COM A LETRA: G"},{"Title":"Bulas de medicamentos com a letra: H","uppercase":"H","borderb_URL":"https://consultaremedios.com.br/haldol/bula","borderb":"Bula do Haldol","borderb_URL1":"https://consultaremedios.com.br/hycamtin/bula","borderb2":"Bula do Hycamtin","borderb_URL3":"https://consultaremedios.com.br/hyzaar/bula","borderb4":"Bula do Hyzaar","borderb_URL5":"https://consultaremedios.com.br/hydrea/bula","borderb6":"Bula do Hydrea","borderb_URL7":"https://consultaremedios.com.br/hydergine/bula","borderb8":"Bula do Hydergine","borderb_URL9":"https://consultaremedios.com.br/hidantal-comprimido/bula","borderb10":"Bula do Hidantal Comprimido","borderb_URL11":"https://consultaremedios.com.br/higroton/bula","borderb12":"Bula do Higroton","borderb_URL13":"https://consultaremedios.com.br/hyperium/bula","borderb14":"Bula do Hyperium","borderb_URL15":"https://consultaremedios.com.br/hemogenin/bula","borderb16":"Bula do Hemogenin","borderb_URL17":"https://consultaremedios.com.br/humectol-d/bula","borderb18":"Bula do Humectol D","borderb_URL19":"https://consultaremedios.com.br/hexomedine/bula","borderb20":"Bula do Hexomedine","borderb_URL21":"https://consultaremedios.com.br/hytrin/bula","borderb22":"Bula do Hytrin","borderb_URL23":"https://consultaremedios.com.br/hemifumarato-de-quetiapina-biosintetica-ache/bula","borderb24":"Bula do Hemifumarato de Quetiapina Biosintética - Aché","borderb_URL25":"https://consultaremedios.com.br/hemifumarato-de-bisoprolol-ems/bula","borderb26":"Bula do Hemifumarato de Bisoprolol EMS","borderb_URL27":"https://consultaremedios.com.br/hemifumarato-de-quetiapina-legrand/bula","borderb28":"Bula do Hemifumarato de Quetiapina Legrand","borderb_URL29":"https://consultaremedios.com.br/hemifumarato-de-quetiapina-ems/bula","borderb30":"Bula do Hemifumarato de Quetiapina EMS","borderb_URL31":"https://consultaremedios.com.br/hemifumarato-de-quetiapina-germed-pharma/bula","borderb32":"Bula do Hemifumarato de Quetiapina Germed Pharma","borderb_URL33":"https://consultaremedios.com.br/hemifumarato-de-quetiapina-biolab-genericos/bula","borderb34":"Bula do Hemifumarato de Quetiapina Biolab Genéricos","borderb_URL35":"https://consultaremedios.com.br/hemifumarato-de-quetiapina-laboratorio-cristalia/bula","borderb36":"Bula do Hemifumarato de Quetiapina Laboratório Cristália","borderb_URL37":"https://consultaremedios.com.br/hamamelis-ec/bula","borderb38":"Bula do Hamamelis EC","btn_URL":"https://consultaremedios.com.br/bulas/h","btn":"TUDO COM A LETRA: H"},{"Title":"Bulas de medicamentos com a letra: I","uppercase":"I","borderb_URL":"https://consultaremedios.com.br/inderal/bula","borderb":"Bula do Inderal","borderb_URL1":"https://consultaremedios.com.br/imosec/bula","borderb2":"Bula do Imosec","borderb_URL3":"https://consultaremedios.com.br/imovane/bula","borderb4":"Bula do Imovane","borderb_URL5":"https://consultaremedios.com.br/ionil-t/bula","borderb6":"Bula do Ionil T","borderb_URL7":"https://consultaremedios.com.br/invega/bula","borderb8":"Bula do Invega","borderb_URL9":"https://consultaremedios.com.br/imuran/bula","borderb10":"Bula do Imuran","borderb_URL11":"https://consultaremedios.com.br/imigran/bula","borderb12":"Bula do Imigran","borderb_URL13":"https://consultaremedios.com.br/isotrex/bula","borderb14":"Bula do Isotrex","borderb_URL15":"https://consultaremedios.com.br/implanon-nxt/bula","borderb16":"Bula do Implanon NXT","borderb_URL17":"https://consultaremedios.com.br/isotrexin/bula","borderb18":"Bula do Isotrexin","borderb_URL19":"https://consultaremedios.com.br/isofarma-solucao-de-fosfato-de-potassio/bula","borderb20":"Bula do Isofarma Solução de Fosfato de Potássio","borderb_URL21":"https://consultaremedios.com.br/indapamida-ems/bula","borderb22":"Bula do Indapamida EMS","borderb_URL23":"https://consultaremedios.com.br/ibuflex-capsula/bula","borderb24":"Bula do Ibuflex Cápsula","borderb_URL25":"https://consultaremedios.com.br/ibuprofeno-comprimido-cimed/bula","borderb26":"Bula do Ibuprofeno Comprimido Cimed","borderb_URL27":"https://consultaremedios.com.br/ibuprofeno-germed-pharma/bula","borderb28":"Bula do Ibuprofeno Germed Pharma","borderb_URL29":"https://consultaremedios.com.br/ibuprofeno-comprimido-ems/bula","borderb30":"Bula do Ibuprofeno Comprimido EMS","borderb_URL31":"https://consultaremedios.com.br/ibuliv-capsula/bula","borderb32":"Bula do Ibuliv Cápsula","borderb_URL33":"https://consultaremedios.com.br/ibuprofeno-gotas-geolab/bula","borderb34":"Bula do Ibuprofeno Gotas Geolab","borderb_URL35":"https://consultaremedios.com.br/iguassina/bula","borderb36":"Bula do Iguassina","borderb_URL37":"https://consultaremedios.com.br/ilaris/bula","borderb38":"Bula do Ilaris","btn_URL":"https://consultaremedios.com.br/bulas/i","btn":"TUDO COM A LETRA: I"},{"Title":"Bulas de medicamentos com a letra: J","uppercase":"J","borderb_URL":"https://consultaremedios.com.br/jumexil/bula","borderb":"Bula do Jumexil","borderb_URL1":"https://consultaremedios.com.br/janumet/bula","borderb2":"Bula do Janumet","borderb_URL3":"https://consultaremedios.com.br/januvia/bula","borderb4":"Bula do Januvia","borderb_URL5":"https://consultaremedios.com.br/jalra-met/bula","borderb6":"Bula do Jalra Met","borderb_URL7":"https://consultaremedios.com.br/jurnista/bula","borderb8":"Bula do Jurnista","borderb_URL9":"https://consultaremedios.com.br/jalra/bula","borderb10":"Bula do Jalra","borderb_URL11":"https://consultaremedios.com.br/juliet/bula","borderb12":"Bula do Juliet","borderb_URL13":"https://consultaremedios.com.br/jevtana/bula","borderb14":"Bula do Jevtana","borderb_URL15":"https://consultaremedios.com.br/javlor/bula","borderb16":"Bula do Javlor","borderb_URL17":"https://consultaremedios.com.br/jardiance/bula","borderb18":"Bula do Jardiance","borderb_URL19":"https://consultaremedios.com.br/janumet-xr/bula","borderb20":"Bula do Janumet XR","borderb_URL21":"https://consultaremedios.com.br/jetrea/bula","borderb22":"Bula do Jetrea","borderb_URL23":"https://consultaremedios.com.br/jp-fisiologico/bula","borderb24":"Bula do JP Fisiológico","borderb_URL25":"https://consultaremedios.com.br/jakavi/bula","borderb26":"Bula do Jakavi","borderb_URL27":"https://consultaremedios.com.br/jofix/bula","borderb28":"Bula do Jofix","borderb_URL29":"https://consultaremedios.com.br/jaque/bula","borderb30":"Bula do Jaque","borderb_URL31":"https://consultaremedios.com.br/junno/bula","borderb32":"Bula do Junno","borderb_URL33":"https://consultaremedios.com.br/juneve/bula","borderb34":"Bula do Juneve","borderb_URL35":"https://consultaremedios.com.br/jivi/bula","borderb36":"Bula do Jivi","borderb_URL37":"https://consultaremedios.com.br/jemperli/bula","borderb38":"Bula do Jemperli","btn_URL":"https://consultaremedios.com.br/bulas/j","btn":"TUDO COM A LETRA: J"},{"Title":"Bulas de medicamentos com a letra: K","uppercase":"K","borderb_URL":"https://consultaremedios.com.br/kytril/bula","borderb":"Bula do Kytril","borderb_URL1":"https://consultaremedios.com.br/kwell/bula","borderb2":"Bula do Kwell","borderb_URL3":"https://consultaremedios.com.br/keflin-neutro/bula","borderb4":"Bula do Keflin Neutro","borderb_URL5":"https://consultaremedios.com.br/keflaxina/bula","borderb6":"Bula do Keflaxina","borderb_URL7":"https://consultaremedios.com.br/klaricid/bula","borderb8":"Bula do Klaricid","borderb_URL9":"https://consultaremedios.com.br/kadcyla/bula","borderb10":"Bula do Kadcyla","borderb_URL11":"https://consultaremedios.com.br/kalloplast/bula","borderb12":"Bula do Kalloplast","borderb_URL13":"https://consultaremedios.com.br/keroxime/bula","borderb14":"Bula do Keroxime","borderb_URL15":"https://consultaremedios.com.br/kronel/bula","borderb16":"Bula do Kronel","borderb_URL17":"https://consultaremedios.com.br/keltrina-plus/bula","borderb18":"Bula do Keltrina Plus","borderb_URL19":"https://consultaremedios.com.br/kalonat/bula","borderb20":"Bula do Kalonat","borderb_URL21":"https://consultaremedios.com.br/kitnos/bula","borderb22":"Bula do Kitnos","borderb_URL23":"https://consultaremedios.com.br/katrizan/bula","borderb24":"Bula do Katrizan","borderb_URL25":"https://consultaremedios.com.br/ketonazol-creme/bula","borderb26":"Bula do Ketonazol Creme","borderb_URL27":"https://consultaremedios.com.br/klimater/bula","borderb28":"Bula do Klimater","borderb_URL29":"https://consultaremedios.com.br/koidexa/bula","borderb30":"Bula do Koidexa","borderb_URL31":"https://consultaremedios.com.br/koide-d/bula","borderb32":"Bula do Kóide D","borderb_URL33":"https://consultaremedios.com.br/kefazol/bula","borderb34":"Bula do Kefazol","borderb_URL35":"https://consultaremedios.com.br/kamillosan/bula","borderb36":"Bula do Kamillosan","borderb_URL37":"https://consultaremedios.com.br/kios/bula","borderb38":"Bula do Kios","btn_URL":"https://consultaremedios.com.br/bulas/k","btn":"TUDO COM A LETRA: K"},{"Title":"Bulas de medicamentos com a letra: L","uppercase":"L","borderb_URL":"https://consultaremedios.com.br/lescol-xl/bula","borderb":"Bula do Lescol XL","borderb_URL1":"https://consultaremedios.com.br/lexotan/bula","borderb2":"Bula do Lexotan","borderb_URL3":"https://consultaremedios.com.br/lopid/bula","borderb4":"Bula do Lopid","borderb_URL5":"https://consultaremedios.com.br/lopressor/bula","borderb6":"Bula do Lopressor","borderb_URL7":"https://consultaremedios.com.br/levitra/bula","borderb8":"Bula do Levitra","borderb_URL9":"https://consultaremedios.com.br/lumigan/bula","borderb10":"Bula do Lumigan","borderb_URL11":"https://consultaremedios.com.br/lamictal/bula","borderb12":"Bula do Lamictal","borderb_URL13":"https://consultaremedios.com.br/libiam/bula","borderb14":"Bula do Libiam","borderb_URL15":"https://consultaremedios.com.br/loprox/bula","borderb16":"Bula do Loprox","borderb_URL17":"https://consultaremedios.com.br/lacrima-plus/bula","borderb18":"Bula do Lacrima Plus","borderb_URL19":"https://consultaremedios.com.br/lanexat/bula","borderb20":"Bula do Lanexat","borderb_URL21":"https://consultaremedios.com.br/lamisilate/bula","borderb22":"Bula do Lamisilate","borderb_URL23":"https://consultaremedios.com.br/lipanon/bula","borderb24":"Bula do Lipanon","borderb_URL25":"https://consultaremedios.com.br/lorax/bula","borderb26":"Bula do Lorax","borderb_URL27":"https://consultaremedios.com.br/losec-mups/bula","borderb28":"Bula do Losec Mups","borderb_URL29":"https://consultaremedios.com.br/lactulona/bula","borderb30":"Bula do Lactulona","borderb_URL31":"https://consultaremedios.com.br/levaquin/bula","borderb32":"Bula do Levaquin","borderb_URL33":"https://consultaremedios.com.br/lioresal/bula","borderb34":"Bula do Lioresal","borderb_URL35":"https://consultaremedios.com.br/lasix/bula","borderb36":"Bula do Lasix","borderb_URL37":"https://consultaremedios.com.br/leponex/bula","borderb38":"Bula do Leponex","btn_URL":"https://consultaremedios.com.br/bulas/l","btn":"TUDO COM A LETRA: L"},{"Title":"Bulas de medicamentos com a letra: M","uppercase":"M","borderb_URL":"https://consultaremedios.com.br/miantrex-cs/bula","borderb":"Bula do Miantrex CS","borderb_URL1":"https://consultaremedios.com.br/mirena/bula","borderb2":"Bula do Mirena","borderb_URL3":"https://consultaremedios.com.br/miticocan/bula","borderb4":"Bula do Miticoçan","borderb_URL5":"https://consultaremedios.com.br/muricalm/bula","borderb6":"Bula do Muricalm","borderb_URL7":"https://consultaremedios.com.br/mydriacyl/bula","borderb8":"Bula do Mydriacyl","borderb_URL9":"https://consultaremedios.com.br/mylanta-plus/bula","borderb10":"Bula do Mylanta Plus","borderb_URL11":"https://consultaremedios.com.br/motilium/bula","borderb12":"Bula do Motilium","borderb_URL13":"https://consultaremedios.com.br/monocordil/bula","borderb14":"Bula do Monocordil","borderb_URL15":"https://consultaremedios.com.br/movatec/bula","borderb16":"Bula do Movatec","borderb_URL17":"https://consultaremedios.com.br/muvinor/bula","borderb18":"Bula do Muvinor","borderb_URL19":"https://consultaremedios.com.br/maxcef/bula","borderb20":"Bula do Maxcef","borderb_URL21":"https://consultaremedios.com.br/marax/bula","borderb22":"Bula do Marax","borderb_URL23":"https://consultaremedios.com.br/megestat/bula","borderb24":"Bula do Megestat","borderb_URL25":"https://consultaremedios.com.br/maalox/bula","borderb26":"Bula do Maalox","borderb_URL27":"https://consultaremedios.com.br/meromax/bula","borderb28":"Bula do Meromax","borderb_URL29":"https://consultaremedios.com.br/merthiolate/bula","borderb30":"Bula do Merthiolate","borderb_URL31":"https://consultaremedios.com.br/micardis/bula","borderb32":"Bula do Micardis","borderb_URL33":"https://consultaremedios.com.br/mucolitic/bula","borderb34":"Bula do Mucolitic","borderb_URL35":"https://consultaremedios.com.br/miosan-caf/bula","borderb36":"Bula do Miosan Caf","borderb_URL37":"https://consultaremedios.com.br/moduretic/bula","borderb38":"Bula do Moduretic","btn_URL":"https://consultaremedios.com.br/bulas/m","btn":"TUDO COM A LETRA: M"},{"Title":"Bulas de medicamentos com a letra: N","uppercase":"N","borderb_URL":"https://consultaremedios.com.br/nebilet/bula","borderb":"Bula do Nebilet","borderb_URL1":"https://consultaremedios.com.br/nexium/bula","borderb2":"Bula do Nexium","borderb_URL3":"https://consultaremedios.com.br/nicorette/bula","borderb4":"Bula do Nicorette","borderb_URL5":"https://consultaremedios.com.br/nutraplus/bula","borderb6":"Bula do Nutraplus","borderb_URL7":"https://consultaremedios.com.br/nolvadex-d/bula","borderb8":"Bula do Nolvadex-D","borderb_URL9":"https://consultaremedios.com.br/naprix-d/bula","borderb10":"Bula do Naprix D","borderb_URL11":"https://consultaremedios.com.br/novonorm/bula","borderb12":"Bula do Novonorm","borderb_URL13":"https://consultaremedios.com.br/navelbine-injetavel/bula","borderb14":"Bula do Navelbine Injetável","borderb_URL15":"https://consultaremedios.com.br/neozine/bula","borderb16":"Bula do Neozine","borderb_URL17":"https://consultaremedios.com.br/nizoral/bula","borderb18":"Bula do Nizoral","borderb_URL19":"https://consultaremedios.com.br/novacort/bula","borderb20":"Bula do Novacort","borderb_URL21":"https://consultaremedios.com.br/naldecon-noite/bula","borderb22":"Bula do Naldecon Noite","borderb_URL23":"https://consultaremedios.com.br/nasonex/bula","borderb24":"Bula do Nasonex","borderb_URL25":"https://consultaremedios.com.br/novalgina-comprimido/bula","borderb26":"Bula do Novalgina Comprimido","borderb_URL27":"https://consultaremedios.com.br/naropin/bula","borderb28":"Bula do Naropin","borderb_URL29":"https://consultaremedios.com.br/nitrencord/bula","borderb30":"Bula do Nitrencord","borderb_URL31":"https://consultaremedios.com.br/naldecon-dia/bula","borderb32":"Bula do Naldecon Dia","borderb_URL33":"https://consultaremedios.com.br/neosaldina/bula","borderb34":"Bula do Neosaldina","borderb_URL35":"https://consultaremedios.com.br/nitroderm-tts/bula","borderb36":"Bula do Nitroderm TTS","borderb_URL37":"https://consultaremedios.com.br/nootropil/bula","borderb38":"Bula do Nootropil","btn_URL":"https://consultaremedios.com.br/bulas/n","btn":"TUDO COM A LETRA: N"},{"Title":"Bulas de medicamentos com a letra: O","uppercase":"O","borderb_URL":"https://consultaremedios.com.br/omcilon-am/bula","borderb":"Bula do Omcilon-AM","borderb_URL1":"https://consultaremedios.com.br/omnaris/bula","borderb2":"Bula do Omnaris","borderb_URL3":"https://consultaremedios.com.br/otosynalar/bula","borderb4":"Bula do Otosynalar","borderb_URL5":"https://consultaremedios.com.br/oroxadin/bula","borderb6":"Bula do Oroxadin","borderb_URL7":"https://consultaremedios.com.br/oceral/bula","borderb8":"Bula do Oceral","borderb_URL9":"https://consultaremedios.com.br/ovestrion-comprimido/bula","borderb10":"Bula do Ovestrion Comprimido","borderb_URL11":"https://consultaremedios.com.br/ovidrel/bula","borderb12":"Bula do Ovidrel","borderb_URL13":"https://consultaremedios.com.br/otrivina/bula","borderb14":"Bula do Otrivina","borderb_URL15":"https://consultaremedios.com.br/onglyza/bula","borderb16":"Bula do Onglyza","borderb_URL17":"https://consultaremedios.com.br/oxycontin/bula","borderb18":"Bula do Oxycontin","borderb_URL19":"https://consultaremedios.com.br/oncodox/bula","borderb20":"Bula do Oncodox","borderb_URL21":"https://consultaremedios.com.br/ofloxacino-legrand/bula","borderb22":"Bula do Ofloxacino Legrand","borderb_URL23":"https://consultaremedios.com.br/oflox/bula","borderb24":"Bula do Oflox","borderb_URL25":"https://consultaremedios.com.br/ofloxacino-germed-pharma/bula","borderb26":"Bula do Ofloxacino Germed Pharma","borderb_URL27":"https://consultaremedios.com.br/ocitocina-blau/bula","borderb28":"Bula do Ocitocina Blau","borderb_URL29":"https://consultaremedios.com.br/oestrogel/bula","borderb30":"Bula do Oestrogel","borderb_URL31":"https://consultaremedios.com.br/oleptal/bula","borderb32":"Bula do Oleptal","borderb_URL33":"https://consultaremedios.com.br/onbrize/bula","borderb34":"Bula do Onbrize","borderb_URL35":"https://consultaremedios.com.br/oncileg/bula","borderb36":"Bula do Oncileg","borderb_URL37":"https://consultaremedios.com.br/oto-betnovate/bula","borderb38":"Bula do Oto-Betnovate","btn_URL":"https://consultaremedios.com.br/bulas/o","btn":"TUDO COM A LETRA: O"},{"Title":"Bulas de medicamentos com a letra: P","uppercase":"P","borderb_URL":"https://consultaremedios.com.br/pantelmin/bula","borderb":"Bula do Pantelmin","borderb_URL1":"https://consultaremedios.com.br/prurizin/bula","borderb2":"Bula do Prurizin","borderb_URL3":"https://consultaremedios.com.br/pariet/bula","borderb4":"Bula do Pariet","borderb_URL5":"https://consultaremedios.com.br/prazol/bula","borderb6":"Bula do Prazol","borderb_URL7":"https://consultaremedios.com.br/pletil/bula","borderb8":"Bula do Pletil","borderb_URL9":"https://consultaremedios.com.br/propecia/bula","borderb10":"Bula do Propecia","borderb_URL11":"https://consultaremedios.com.br/propil/bula","borderb12":"Bula do Propil","borderb_URL13":"https://consultaremedios.com.br/polvilho-antisseptico-granado/bula","borderb14":"Bula do Polvilho Antisséptico Granado","borderb_URL15":"https://consultaremedios.com.br/plaquinol/bula","borderb16":"Bula do Plaquinol","borderb_URL17":"https://consultaremedios.com.br/pyridium/bula","borderb18":"Bula do Pyridium","borderb_URL19":"https://consultaremedios.com.br/pamelor/bula","borderb20":"Bula do Pamelor","borderb_URL21":"https://consultaremedios.com.br/puran-t4/bula","borderb22":"Bula do Puran T4","borderb_URL23":"https://consultaremedios.com.br/pantozol/bula","borderb24":"Bula do Pantozol","borderb_URL25":"https://consultaremedios.com.br/parlodel/bula","borderb26":"Bula do Parlodel","borderb_URL27":"https://consultaremedios.com.br/plasil-comprimido/bula","borderb28":"Bula do Plasil Comprimido","borderb_URL29":"https://consultaremedios.com.br/proflam-comprimido/bula","borderb30":"Bula do Proflam Comprimido","borderb_URL31":"https://consultaremedios.com.br/psorex/bula","borderb32":"Bula do Psorex","borderb_URL33":"https://consultaremedios.com.br/prinzide/bula","borderb34":"Bula do Prinzide","borderb_URL35":"https://consultaremedios.com.br/prolopa/bula","borderb36":"Bula do Prolopa","borderb_URL37":"https://consultaremedios.com.br/pilocarpina-allergan/bula","borderb38":"Bula do Pilocarpina Allergan","btn_URL":"https://consultaremedios.com.br/bulas/p","btn":"TUDO COM A LETRA: P"},{"Title":"Bulas de medicamentos com a letra: Q","uppercase":"Q","borderb_URL":"https://consultaremedios.com.br/quadriderm/bula","borderb":"Bula do Quadriderm","borderb_URL1":"https://consultaremedios.com.br/qiftrim/bula","borderb2":"Bula do Qiftrim","borderb_URL3":"https://consultaremedios.com.br/quadribeta/bula","borderb4":"Bula do Quadribeta","borderb_URL5":"https://consultaremedios.com.br/quadritop/bula","borderb6":"Bula do Quadritop","borderb_URL7":"https://consultaremedios.com.br/quinoflox/bula","borderb8":"Bula do Quinoflox","borderb_URL9":"https://consultaremedios.com.br/questran-light/bula","borderb10":"Bula do Questran Light","borderb_URL11":"https://consultaremedios.com.br/qlaira/bula","borderb12":"Bula do Qlaira","borderb_URL13":"https://consultaremedios.com.br/queimalive/bula","borderb14":"Bula do Queimalive","borderb_URL15":"https://consultaremedios.com.br/quitlis/bula","borderb16":"Bula do Quitlis","borderb_URL17":"https://consultaremedios.com.br/quinacris/bula","borderb18":"Bula do Quinacris","borderb_URL19":"https://consultaremedios.com.br/quelatus/bula","borderb20":"Bula do Quelatus","borderb_URL21":"https://consultaremedios.com.br/quadrilon/bula","borderb22":"Bula do Quadrilon","borderb_URL23":"https://consultaremedios.com.br/quadrineo/bula","borderb24":"Bula do Quadrineo","borderb_URL25":"https://consultaremedios.com.br/quemicetina/bula","borderb26":"Bula do Quemicetina","borderb_URL27":"https://consultaremedios.com.br/queopine/bula","borderb28":"Bula do Queopine","borderb_URL29":"https://consultaremedios.com.br/querok/bula","borderb30":"Bula do Querok","borderb_URL31":"https://consultaremedios.com.br/quetipin/bula","borderb32":"Bula do Quetipin","borderb_URL33":"https://consultaremedios.com.br/quetros/bula","borderb34":"Bula do Quetros","borderb_URL35":"https://consultaremedios.com.br/quet-xr/bula","borderb36":"Bula do Quet XR","borderb_URL37":"https://consultaremedios.com.br/quetibux/bula","borderb38":"Bula do Quetibux","btn_URL":"https://consultaremedios.com.br/bulas/q","btn":"TUDO COM A LETRA: Q"},{"Title":"Bulas de medicamentos com a letra: R","uppercase":"R","borderb_URL":"https://consultaremedios.com.br/rifocina-spray/bula","borderb":"Bula do Rifocina Spray","borderb_URL1":"https://consultaremedios.com.br/revatio/bula","borderb2":"Bula do Revatio","borderb_URL3":"https://consultaremedios.com.br/rilutek/bula","borderb4":"Bula do Rilutek","borderb_URL5":"https://consultaremedios.com.br/resfenol/bula","borderb6":"Bula do Resfenol","borderb_URL7":"https://consultaremedios.com.br/retemic/bula","borderb8":"Bula do Retemic","borderb_URL9":"https://consultaremedios.com.br/rubidex/bula","borderb10":"Bula do Rubidex","borderb_URL11":"https://consultaremedios.com.br/rapifen/bula","borderb12":"Bula do Rapifen","borderb_URL13":"https://consultaremedios.com.br/rasilez/bula","borderb14":"Bula do Rasilez","borderb_URL15":"https://consultaremedios.com.br/reparil/bula","borderb16":"Bula do Reparil","borderb_URL17":"https://consultaremedios.com.br/revectina/bula","borderb18":"Bula do Revectina","borderb_URL19":"https://consultaremedios.com.br/rivotril/bula","borderb20":"Bula do Rivotril","borderb_URL21":"https://consultaremedios.com.br/rinigran/bula","borderb22":"Bula do Rinigran","borderb_URL23":"https://consultaremedios.com.br/renitec/bula","borderb24":"Bula do Renitec","borderb_URL25":"https://consultaremedios.com.br/rino-lastin/bula","borderb26":"Bula do Rino-Lastin","borderb_URL27":"https://consultaremedios.com.br/refresh/bula","borderb28":"Bula do Refresh","borderb_URL29":"https://consultaremedios.com.br/rohypnol/bula","borderb30":"Bula do Rohypnol","borderb_URL31":"https://consultaremedios.com.br/ribavirin/bula","borderb32":"Bula do Ribavirin","borderb_URL33":"https://consultaremedios.com.br/relestat/bula","borderb34":"Bula do Relestat","borderb_URL35":"https://consultaremedios.com.br/restasis/bula","borderb36":"Bula do Restasis","borderb_URL37":"https://consultaremedios.com.br/ritmonorm/bula","borderb38":"Bula do Ritmonorm","btn_URL":"https://consultaremedios.com.br/bulas/r","btn":"TUDO COM A LETRA: R"},{"Title":"Bulas de medicamentos com a letra: S","uppercase":"S","borderb_URL":"https://consultaremedios.com.br/splendil/bula","borderb":"Bula do Splendil","borderb_URL1":"https://consultaremedios.com.br/sonridor-caf/bula","borderb2":"Bula do Sonridor Caf","borderb_URL3":"https://consultaremedios.com.br/sotacor/bula","borderb4":"Bula do Sotacor","borderb_URL5":"https://consultaremedios.com.br/secnidal/bula","borderb6":"Bula do Secnidal","borderb_URL7":"https://consultaremedios.com.br/stilnox/bula","borderb8":"Bula do Stilnox","borderb_URL9":"https://consultaremedios.com.br/selopress/bula","borderb10":"Bula do Selopress","borderb_URL11":"https://consultaremedios.com.br/sufenta/bula","borderb12":"Bula do Sufenta","borderb_URL13":"https://consultaremedios.com.br/sporanox/bula","borderb14":"Bula do Sporanox","borderb_URL15":"https://consultaremedios.com.br/suladrin/bula","borderb16":"Bula do Suladrin","borderb_URL17":"https://consultaremedios.com.br/solu-medrol/bula","borderb18":"Bula do Solu-Medrol","borderb_URL19":"https://consultaremedios.com.br/sandostatin/bula","borderb20":"Bula do Sandostatin","borderb_URL21":"https://consultaremedios.com.br/syntocinon-spray-nasal/bula","borderb22":"Bula do Syntocinon Spray Nasal","borderb_URL23":"https://consultaremedios.com.br/secotex/bula","borderb24":"Bula do Secotex","borderb_URL25":"https://consultaremedios.com.br/sorcal/bula","borderb26":"Bula do Sorcal","borderb_URL27":"https://consultaremedios.com.br/seroquel/bula","borderb28":"Bula do Seroquel","borderb_URL29":"https://consultaremedios.com.br/stugeron/bula","borderb30":"Bula do Stugeron","borderb_URL31":"https://consultaremedios.com.br/sirdalud/bula","borderb32":"Bula do Sirdalud","borderb_URL33":"https://consultaremedios.com.br/sonridor/bula","borderb34":"Bula do Sonridor","borderb_URL35":"https://consultaremedios.com.br/selozok-fix/bula","borderb36":"Bula do Selozok Fix","borderb_URL37":"https://consultaremedios.com.br/spiriva-respimat/bula","borderb38":"Bula do Spiriva Respimat","btn_URL":"https://consultaremedios.com.br/bulas/s","btn":"TUDO COM A LETRA: S"},{"Title":"Bulas de medicamentos com a letra: T","uppercase":"T","borderb_URL":"https://consultaremedios.com.br/taxol/bula","borderb":"Bula do Taxol","borderb_URL1":"https://consultaremedios.com.br/temodal/bula","borderb2":"Bula do Temodal","borderb_URL3":"https://consultaremedios.com.br/tenoretic/bula","borderb4":"Bula do Tenoretic","borderb_URL5":"https://consultaremedios.com.br/targocid/bula","borderb6":"Bula do Targocid","borderb_URL7":"https://consultaremedios.com.br/tecnocris/bula","borderb8":"Bula do Tecnocris","borderb_URL9":"https://consultaremedios.com.br/tagamet/bula","borderb10":"Bula do Tagamet","borderb_URL11":"https://consultaremedios.com.br/tecnovorin/bula","borderb12":"Bula do Tecnovorin","borderb_URL13":"https://consultaremedios.com.br/tetmosol/bula","borderb14":"Bula do Tetmosol","borderb_URL15":"https://consultaremedios.com.br/timoptol/bula","borderb16":"Bula do Timoptol","borderb_URL17":"https://consultaremedios.com.br/tracleer/bula","borderb18":"Bula do Tracleer","borderb_URL19":"https://consultaremedios.com.br/trifamox-ibl/bula","borderb20":"Bula do Trifamox IBL","borderb_URL21":"https://consultaremedios.com.br/trusopt/bula","borderb22":"Bula do Trusopt","borderb_URL23":"https://consultaremedios.com.br/tofranil/bula","borderb24":"Bula do Tofranil","borderb_URL25":"https://consultaremedios.com.br/tralen/bula","borderb26":"Bula do Tralen","borderb_URL27":"https://consultaremedios.com.br/topamax/bula","borderb28":"Bula do Topamax","borderb_URL29":"https://consultaremedios.com.br/travatan/bula","borderb30":"Bula do Travatan","borderb_URL31":"https://consultaremedios.com.br/tobradex/bula","borderb32":"Bula do Tobradex","borderb_URL33":"https://consultaremedios.com.br/taxotere/bula","borderb34":"Bula do Taxotere","borderb_URL35":"https://consultaremedios.com.br/trental/bula","borderb36":"Bula do Trental","borderb_URL37":"https://consultaremedios.com.br/tazocin/bula","borderb38":"Bula do Tazocin","btn_URL":"https://consultaremedios.com.br/bulas/t","btn":"TUDO COM A LETRA: T"},{"Title":"Bulas de medicamentos com a letra: U","uppercase":"U","borderb_URL":"https://consultaremedios.com.br/ultracet/bula","borderb":"Bula do Ultracet","borderb_URL1":"https://consultaremedios.com.br/ultiva/bula","borderb2":"Bula do Ultiva","borderb_URL3":"https://consultaremedios.com.br/unifepim/bula","borderb4":"Bula do Unifepim","borderb_URL5":"https://consultaremedios.com.br/ulcerocin/bula","borderb6":"Bula do Ulcerocin","borderb_URL7":"https://consultaremedios.com.br/ultidin-xarope/bula","borderb8":"Bula do Ultidin Xarope","borderb_URL9":"https://consultaremedios.com.br/ultravist/bula","borderb10":"Bula do Ultravist","borderb_URL11":"https://consultaremedios.com.br/urovit/bula","borderb12":"Bula do Urovit","borderb_URL13":"https://consultaremedios.com.br/uni-carbamaz/bula","borderb14":"Bula do Uni-Carbamaz","borderb_URL15":"https://consultaremedios.com.br/uroseptal/bula","borderb16":"Bula do Uroseptal","borderb_URL17":"https://consultaremedios.com.br/unigrip/bula","borderb18":"Bula do Unigrip","borderb_URL19":"https://consultaremedios.com.br/urografina/bula","borderb20":"Bula do Urografina","borderb_URL21":"https://consultaremedios.com.br/ultraproct-ldo/bula","borderb22":"Bula do Ultraproct LDO","borderb_URL23":"https://consultaremedios.com.br/ursacol/bula","borderb24":"Bula do Ursacol","borderb_URL25":"https://consultaremedios.com.br/ulcestop/bula","borderb26":"Bula do Ulcestop","borderb_URL27":"https://consultaremedios.com.br/ulcinax/bula","borderb28":"Bula do Ulcinax","borderb_URL29":"https://consultaremedios.com.br/unasyn-injetavel/bula","borderb30":"Bula do Unasyn Injetável","borderb_URL31":"https://consultaremedios.com.br/uni-clonazepax-gotas/bula","borderb32":"Bula do Uni-Clonazepax Gotas","borderb_URL33":"https://consultaremedios.com.br/uni-imiprax/bula","borderb34":"Bula do Uni Imiprax","borderb_URL35":"https://consultaremedios.com.br/unifental/bula","borderb36":"Bula do Unifental","borderb_URL37":"https://consultaremedios.com.br/unianf/bula","borderb38":"Bula do Unianf","btn_URL":"https://consultaremedios.com.br/bulas/u","btn":"TUDO COM A LETRA: U"},{"Title":"Bulas de medicamentos com a letra: V","uppercase":"V","borderb_URL":"https://consultaremedios.com.br/vibramicina/bula","borderb":"Bula do Vibramicina","borderb_URL1":"https://consultaremedios.com.br/vitanol-a/bula","borderb2":"Bula do Vitanol-A","borderb_URL3":"https://consultaremedios.com.br/vancocina-cp/bula","borderb4":"Bula do Vancocina CP","borderb_URL5":"https://consultaremedios.com.br/valium/bula","borderb6":"Bula do Valium","borderb_URL7":"https://consultaremedios.com.br/vytorin/bula","borderb8":"Bula do Vytorin","borderb_URL9":"https://consultaremedios.com.br/velcade/bula","borderb10":"Bula do Velcade","borderb_URL11":"https://consultaremedios.com.br/vascase/bula","borderb12":"Bula do Vascase","borderb_URL13":"https://consultaremedios.com.br/vfend/bula","borderb14":"Bula do Vfend","borderb_URL15":"https://consultaremedios.com.br/valtrex/bula","borderb16":"Bula do Valtrex","borderb_URL17":"https://consultaremedios.com.br/visipaque/bula","borderb18":"Bula do Visipaque","borderb_URL19":"https://consultaremedios.com.br/vitacid-acne/bula","borderb20":"Bula do Vitacid Acne","borderb_URL21":"https://consultaremedios.com.br/vumon/bula","borderb22":"Bula do Vumon","borderb_URL23":"https://consultaremedios.com.br/visudyne/bula","borderb24":"Bula do Visudyne","borderb_URL25":"https://consultaremedios.com.br/vigamed/bula","borderb26":"Bula do Vigamed","borderb_URL27":"https://consultaremedios.com.br/vastarel-mr/bula","borderb28":"Bula do Vastarel MR","borderb_URL29":"https://consultaremedios.com.br/vigamox/bula","borderb30":"Bula do Vigamox","borderb_URL31":"https://consultaremedios.com.br/valcyte/bula","borderb32":"Bula do Valcyte","borderb_URL33":"https://consultaremedios.com.br/vacina-influenza-trivalente-subunitaria-e-inativada-novartis/bula","borderb34":"Bula do Vacina Influenza Trivalente (Subunitária e Inativada) Novartis","borderb_URL35":"https://consultaremedios.com.br/vacina-influenza-trivalente-fragmentada-inativada-gsk/bula","borderb36":"Bula do Vacina Influenza Trivalente (Fragmentada, Inativada) GSK","borderb_URL37":"https://consultaremedios.com.br/vagi-c/bula","borderb38":"Bula do Vagi C","btn_URL":"https://consultaremedios.com.br/bulas/v","btn":"TUDO COM A LETRA: V"},{"Title":"Bulas de medicamentos com a letra: W","uppercase":"W","borderb_URL":"https://consultaremedios.com.br/wartec/bula","borderb":"Bula do Wartec","borderb_URL1":"https://consultaremedios.com.br/wellbutrin-xl/bula","borderb2":"Bula do Wellbutrin XL","borderb_URL3":"https://consultaremedios.com.br/wonilin/bula","borderb4":"Bula do Wonilin","borderb_URL5":"https://consultaremedios.com.br/wintomylon/bula","borderb6":"Bula do Wintomylon","borderb_URL7":"https://consultaremedios.com.br/warfarin/bula","borderb8":"Bula do Warfarin","borderb_URL9":"https://consultaremedios.com.br/winter-ap/bula","borderb10":"Bula do Winter AP","borderb_URL11":"https://consultaremedios.com.br/wilate/bula","borderb12":"Bula do Wilate","borderb_URL13":"https://consultaremedios.com.br/wilfactin/bula","borderb14":"Bula do Wilfactin","borderb_URL15":"https://consultaremedios.com.br/winduza/bula","borderb16":"Bula do Winduza","borderb_URL17":"https://consultaremedios.com.br/wosulin-r/bula","borderb18":"Bula do Wosulin-R","borderb_URL19":"https://consultaremedios.com.br/wosulin-70-30/bula","borderb20":"Bula do Wosulin-70/30","borderb_URL21":"https://consultaremedios.com.br/wosulin-n/bula","borderb22":"Bula do Wosulin-N","borderb_URL23":"https://consultaremedios.com.br/weletuss/bula","borderb24":"Bula do Weletuss","borderb_URL25":"https://consultaremedios.com.br/waryz/bula","borderb26":"Bula do Waryz","borderb_URL27":"https://consultaremedios.com.br/willentine/bula","borderb28":"Bula do Willentine","borderb_URL29":"https://consultaremedios.com.br/wash-in/bula","borderb30":"Bula do Wash In","borderb_URL31":"https://consultaremedios.com.br/wegovy/bula","borderb32":"Bula do Wegovy","borderb_URL33":"https://consultaremedios.com.br/welireg/bula","borderb34":"Bula do Welireg","borderb_URL35":"https://consultaremedios.com.br/weno-dh/bula","borderb36":"Bula do Weno Dh","borderb_URL37":"https://consultaremedios.com.br/waylivra/bula","borderb38":"Bula do Waylivra","btn_URL":"https://consultaremedios.com.br/bulas/w","btn":"TUDO COM A LETRA: W"},{"Title":"Bulas de medicamentos com a letra: X","uppercase":"X","borderb_URL":"https://consultaremedios.com.br/xenical/bula","borderb":"Bula do Xenical","borderb_URL1":"https://consultaremedios.com.br/xyloproct/bula","borderb2":"Bula do Xyloproct","borderb_URL3":"https://consultaremedios.com.br/xalatan/bula","borderb4":"Bula do Xalatan","borderb_URL5":"https://consultaremedios.com.br/xalacom/bula","borderb6":"Bula do Xalacom","borderb_URL7":"https://consultaremedios.com.br/xatral-od/bula","borderb8":"Bula do Xatral OD","borderb_URL9":"https://consultaremedios.com.br/xeloda/bula","borderb10":"Bula do Xeloda","borderb_URL11":"https://consultaremedios.com.br/xarope-guaco-melpoejo/bula","borderb12":"Bula do Xarope Guaco - Melpoejo","borderb_URL13":"https://consultaremedios.com.br/xarope-44e/bula","borderb14":"Bula do Xarope 44E","borderb_URL15":"https://consultaremedios.com.br/xarope-neo/bula","borderb16":"Bula do Xarope Neo","borderb_URL17":"https://consultaremedios.com.br/xarope-de-guaco-natulab/bula","borderb18":"Bula do Xarope de Guaco Natulab","borderb_URL19":"https://consultaremedios.com.br/xefo/bula","borderb20":"Bula do Xefo","borderb_URL21":"https://consultaremedios.com.br/xarelto/bula","borderb22":"Bula do Xarelto","borderb_URL23":"https://consultaremedios.com.br/xarope-de-guaco-belfar/bula","borderb24":"Bula do Xarope de Guaco Belfar","borderb_URL25":"https://consultaremedios.com.br/xantinon-complex/bula","borderb26":"Bula do Xantinon Complex","borderb_URL27":"https://consultaremedios.com.br/xarope-santo-antonio/bula","borderb28":"Bula do Xarope Santo Antonio","borderb_URL29":"https://consultaremedios.com.br/xylestesin-com-vasosonstritor/bula","borderb30":"Bula do Xylestesin Com Vasoconstritor","borderb_URL31":"https://consultaremedios.com.br/xylocaina-pomada/bula","borderb32":"Bula do Xylocaína Pomada","borderb_URL33":"https://consultaremedios.com.br/xeomin/bula","borderb34":"Bula do Xeomin","borderb_URL35":"https://consultaremedios.com.br/xantinon/bula","borderb36":"Bula do Xantinon","borderb_URL37":"https://consultaremedios.com.br/xolair/bula","borderb38":"Bula do Xolair","btn_URL":"https://consultaremedios.com.br/bulas/x","btn":"TUDO COM A LETRA: X"},{"Title":"Bulas de medicamentos com a letra: Y","uppercase":"Y","borderb_URL":"https://consultaremedios.com.br/yomax/bula","borderb":"Bula do Yomax","borderb_URL1":"https://consultaremedios.com.br/yaz/bula","borderb2":"Bula do Yaz","borderb_URL3":"https://consultaremedios.com.br/yasmin/bula","borderb4":"Bula do Yasmin","borderb_URL5":"https://consultaremedios.com.br/yervoy/bula","borderb6":"Bula do Yervoy","borderb_URL7":"https://consultaremedios.com.br/yang-30/bula","borderb8":"Bula do Yang 30","borderb_URL9":"https://consultaremedios.com.br/ylana/bula","borderb10":"Bula do Ylana","borderb_URL11":"https://consultaremedios.com.br/yondelis/bula","borderb12":"Bula do Yondelis","borderb_URL13":"https://consultaremedios.com.br/yaz-flex/bula","borderb14":"Bula do Yaz Flex","borderb_URL15":"https://consultaremedios.com.br/yvi/bula","borderb16":"Bula do Yvi","borderb_URL17":"https://consultaremedios.com.br/yescarta/bula","borderb18":"Bula do Yescarta","borderb_URL19":"https://consultaremedios.com.br/yuflyma/bula","borderb20":"Bula do Yuflyma","borderb_URL21":"https://consultaremedios.com.br/yesom/bula","borderb22":"Bula do Yesom","borderb_URL23":"https://consultaremedios.com.br/yupelri/bula","borderb24":"Bula do Yupelri","borderb_URL25":"","borderb26":"","borderb_URL27":"","borderb28":"","borderb_URL29":"","borderb30":"","borderb_URL31":"","borderb32":"","borderb_URL33":"","borderb34":"","borderb_URL35":"","borderb36":"","borderb_URL37":"","borderb38":"","btn_URL":"https://consultaremedios.com.br/bulas/y","btn":"TUDO COM A LETRA: Y"},{"Title":"Bulas de medicamentos com a letra: Z","uppercase":"Z","borderb_URL":"https://consultaremedios.com.br/zinacef/bula","borderb":"Bula do Zinacef","borderb_URL1":"https://consultaremedios.com.br/zovirax-creme/bula","borderb2":"Bula do Zovirax Creme","borderb_URL3":"https://consultaremedios.com.br/zoltec/bula","borderb4":"Bula do Zoltec","borderb_URL5":"https://consultaremedios.com.br/zaditen-solucao-oftalmica/bula","borderb6":"Bula do Zaditen Solução Oftálmica","borderb_URL7":"https://consultaremedios.com.br/zavedos/bula","borderb8":"Bula do Zavedos","borderb_URL9":"https://consultaremedios.com.br/zestril/bula","borderb10":"Bula do Zestril","borderb_URL11":"https://consultaremedios.com.br/zomig/bula","borderb12":"Bula do Zomig","borderb_URL13":"https://consultaremedios.com.br/zocor/bula","borderb14":"Bula do Zocor","borderb_URL15":"https://consultaremedios.com.br/zinnat/bula","borderb16":"Bula do Zinnat","borderb_URL17":"https://consultaremedios.com.br/zitromax-iv/bula","borderb18":"Bula do Zitromax IV","borderb_URL19":"https://consultaremedios.com.br/zoladex/bula","borderb20":"Bula do Zoladex","borderb_URL21":"https://consultaremedios.com.br/zymar/bula","borderb22":"Bula do Zymar","borderb_URL23":"https://consultaremedios.com.br/zyloric/bula","borderb24":"Bula do Zyloric","borderb_URL25":"https://consultaremedios.com.br/zyxem/bula","borderb26":"Bula do Zyxem","borderb_URL27":"https://consultaremedios.com.br/ziagenavir/bula","borderb28":"Bula do Ziagenavir","borderb_URL29":"https://consultaremedios.com.br/zelmac/bula","borderb30":"Bula do Zelmac","borderb_URL31":"https://consultaremedios.com.br/zanidip/bula","borderb32":"Bula do Zanidip","borderb_URL33":"https://consultaremedios.com.br/zyvox/bula","borderb34":"Bula do Zyvox","borderb_URL35":"https://consultaremedios.com.br/zilaricina/bula","borderb36":"Bula do Zilaricina","borderb_URL37":"https://consultaremedios.com.br/zarator/bula","borderb38":"Bula do Zarator","btn_URL":"https://consultaremedios.com.br/bulas/z","btn":"TUDO COM A LETRA: Z"},{"Title":"Bulas de medicamentos com a letra: 0-9","uppercase":"0-9","borderb_URL":"","borderb":"","borderb_URL1":"","borderb2":"","borderb_URL3":"","borderb4":"","borderb_URL5":"","borderb6":"","borderb_URL7":"","borderb8":"","borderb_URL9":"","borderb10":"","borderb_URL11":"","borderb12":"","borderb_URL13":"","borderb14":"","borderb_URL15":"","borderb16":"","borderb_URL17":"","borderb18":"","borderb_URL19":"","borderb20":"","borderb_URL21":"","borderb22":"","borderb_URL23":"","borderb24":"","borderb_URL25":"","borderb26":"","borderb_URL27":"","borderb28":"","borderb_URL29":"","borderb30":"","borderb_URL31":"","borderb32":"","borderb_URL33":"","borderb34":"","borderb_URL35":"","borderb36":"","borderb_URL37":"","borderb38":"","btn_URL":"https://consultaremedios.com.br/bulas/0-9","btn":"TUDO COM A LETRA: 0-9"}]